pytest_sherlock/__init__.py
pytest_sherlock/_version.py
pytest_sherlock/binary_tree_search.py
pytest_sherlock/plugin.py
pytest_sherlock/sherlock.py
pytest_sherlock-0.3.4.dist-info/LICENSE
pytest_sherlock-0.3.4.dist-info/METADATA
pytest_sherlock-0.3.4.dist-info/WHEEL
pytest_sherlock-0.3.4.dist-info/entry_points.txt
pytest_sherlock-0.3.4.dist-info/top_level.txt
pytest_sherlock-0.3.4.dist-info/RECORD
