Metadata-Version: 2.1
Name: pytest-sherlock
Version: 0.3.4
Summary: pytest plugin help to find coupled tests
Home-page: https://github.com/DKorytkin/pytest-sherlock
Author: Denys Korytkin
Author-email: dkorytkin@gmail.com
License: MIT license
Keywords: py.test,pytest,flaky tests,coupled tests,debug tests
Classifier: Framework :: Pytest
Classifier: Development Status :: 5 - Production/Stable
Classifier: Programming Language :: Python :: 3.7
Classifier: Programming Language :: Python :: 3.8
Classifier: Programming Language :: Python :: 3.10
Classifier: Topic :: Software Development :: Quality Assurance
Classifier: Topic :: Software Development :: Testing
Classifier: Topic :: Utilities
Requires-Python: >=3.7
License-File: LICENSE
Requires-Dist: setuptools >=28.8.0
Requires-Dist: pytest >=3.5.1
Requires-Dist: six >=1.13.0
